storyweaver/Dockerfile
storyweaver/dev.sh
storyweaver/docker-compose.yaml
storyweaver/setup_storybook.py
storyweaver-0.1.0.dist-info/METADATA
storyweaver-0.1.0.dist-info/WHEEL
storyweaver-0.1.0.dist-info/RECORD
