Metadata-Version: 2.1
Name: storyweaver
Version: 0.1.0
Summary: Sets up React with Storybook for component-driven development, including a FastAPI server to mock API responses from user-generated JSON files. Automates Storybook configuration, story generation, and optional mock server startup.
License: MIT
Author: Ali Tavallaie
Author-email: a.tavallaie@gmail.com
Requires-Python: >=3.10,<4.0
Classifier: License :: OSI Approved :: MIT License
Classifier: Programming Language :: Python :: 3
Classifier: Programming Language :: Python :: 3.10
Classifier: Programming Language :: Python :: 3.11
Classifier: Programming Language :: Python :: 3.12
